kpath/__init__.py
kpath/kpath.py
kpath-0.0.2.dist-info/METADATA
kpath-0.0.2.dist-info/WHEEL
kpath-0.0.2.dist-info/top_level.txt
kpath-0.0.2.dist-info/RECORD
