Metadata-Version: 2.1
Name: kpath
Version: 0.0.2
Summary: python path utils
Home-page: https://github.com/kkristof200/pypaths
Author: Kristof
License: UNKNOWN
Platform: UNKNOWN
Classifier: Programming Language :: Python :: 3
Classifier: License :: OSI Approved :: MIT License
Classifier: Operating System :: OS Independent
Requires-Python: >=3.5
